freeze_one/__init__.py
freeze_one/__main__.py
freeze_one-0.2.1.dist-info/licenses/LICENSE.md
freeze_one-0.2.1.dist-info/WHEEL
freeze_one-0.2.1.dist-info/METADATA
freeze_one-0.2.1.dist-info/RECORD
