Metadata-Version: 2.4
Name: freeze_one
Version: 0.2.1
Summary: Get the 'pip freeze' line for one package
Author-email: Gareth Davidson <gaz@bitplane.net>
License-File: LICENSE.md
Requires-Dist: pip>=23
Requires-Dist: flake8 ; extra == "dev"
Requires-Dist: pre-commit ; extra == "dev"
Requires-Dist: pytest ; extra == "dev"
Requires-Dist: coverage ; extra == "dev"
Requires-Dist: pytest-cov ; extra == "dev"
Requires-Dist: build ; extra == "dev"
Requires-Dist: twine ; extra == "dev"
Provides-Extra: dev
